gmalthgtparser/__init__.py
gmalthgtparser/parser.py
gmalthgtparser-1.1.0.dist-info/DESCRIPTION.rst
gmalthgtparser-1.1.0.dist-info/METADATA
gmalthgtparser-1.1.0.dist-info/RECORD
gmalthgtparser-1.1.0.dist-info/WHEEL
gmalthgtparser-1.1.0.dist-info/metadata.json
gmalthgtparser-1.1.0.dist-info/top_level.txt
