Metadata-Version: 2.0
Name: gmalthgtparser
Version: 1.1.0
Summary: Parse HGT files
Home-page: http://github.com/gmalt/hgtparser
Author: Jonathan Bouzekri
Author-email: jonathan.bouzekri@gmail.com
License: MIT
Keywords: parser,hgt,srtm,file
Platform: UNKNOWN
Classifier: Development Status :: 5 - Production/Stable
Classifier: Environment :: Plugins
Classifier: License :: OSI Approved :: MIT License
Classifier: Programming Language :: Python :: 2.7
Classifier: Programming Language :: Python :: 3.4
Classifier: Programming Language :: Python :: 3.5
Classifier: Programming Language :: Python :: 3.6
Classifier: Intended Audience :: Developers
Classifier: Topic :: Scientific/Engineering :: GIS
Classifier: Topic :: Utilities
Provides-Extra: test
Requires-Dist: pytest; extra == 'test'
Requires-Dist: flake8; extra == 'test'
Requires-Dist: mock; extra == 'test'
